ng2web/__init__.py
ng2web/__main__.py
ng2web/ng2web.py
ng2web/py.typed
ng2web/templates/about.html
ng2web/templates/base.css
ng2web/templates/base.html
ng2web/templates/entry.html
ng2web/templates/inc/nav-link.html
ng2web/templates/long.html
ng2web/templates/short.html
ng2web-1.5.1.dist-info/WHEEL
ng2web-1.5.1.dist-info/entry_points.txt
ng2web-1.5.1.dist-info/METADATA
ng2web-1.5.1.dist-info/RECORD
