Metadata-Version: 2.4
Name: ng2web
Version: 1.5.1
Summary: Norton Guide to HTML conversion tool
Keywords: library,dbase,clipper,norton,guide,reader,converter,html
Author: Dave Pearson
Author-email: Dave Pearson <davep@davep.org>
License-Expression: GPL-3.0-or-later
Classifier: Development Status :: 5 - Production/Stable
Classifier: Environment :: Console
Classifier: Intended Audience :: Developers
Classifier: Intended Audience :: Information Technology
Classifier: Operating System :: OS Independent
Classifier: Programming Language :: Python :: 3 :: Only
Classifier: Programming Language :: Python :: 3
Classifier: Programming Language :: Python :: 3.10
Classifier: Programming Language :: Python :: 3.11
Classifier: Programming Language :: Python :: 3.12
Classifier: Programming Language :: Python :: 3.13
Classifier: Programming Language :: Python :: 3.14
Classifier: Topic :: Documentation
Classifier: Topic :: Software Development :: Documentation
Classifier: Topic :: Text Processing :: Markup :: HTML
Classifier: Topic :: Text Processing :: Markup
Classifier: Topic :: Utilities
Classifier: Typing :: Typed
Requires-Dist: ngdb>=0.12.0
Requires-Dist: jinja2>=3.1.6
Requires-Dist: typing-extensions>=4.12.2
Requires-Dist: markupsafe>=3.0.2
Requires-Python: >=3.10
Project-URL: Discussions, https://github.com/davep/ng2web/discussions
Project-URL: Documentation, https://ng2web.davep.dev/
Project-URL: Homepage, https://ng2web.davep.dev/
Project-URL: Issues, https://github.com/davep/ng2web/issues
Project-URL: Repository, https://github.com/davep/ng2web
Project-URL: Source, https://github.com/davep/ng2web
